fastapi_trace/__init__.py
fastapi_trace/config.py
fastapi_trace/context.py
fastapi_trace/integration_examples.py
fastapi_trace/logging_filters.py
fastapi_trace/middleware.py
fastapi_trace_middleware-1.0.3.dist-info/licenses/LICENSE
fastapi_trace_middleware-1.0.3.dist-info/METADATA
fastapi_trace_middleware-1.0.3.dist-info/WHEEL
fastapi_trace_middleware-1.0.3.dist-info/top_level.txt
fastapi_trace_middleware-1.0.3.dist-info/RECORD
